Workbook

Sheet Info
L4: PRODUCT ADD | N4: PRODUCT FORM
L5: CUSTOMER ADD | N5: CUSTOMER FORM
L6: SUPPLIER ADD | N6: SUPPLIER FORM
L7: INVENTORY ADD | N7: Purchase Order
L8: INVENTORY LESS | N8: Sale Order
L10: REPORTS
L11: PURCHASE REPORT | N11: PURCHASE REPORT FROM DATE TO DATE
L12: SALE REPORT | N12: SALE REPORT FROM DATE TO DATE
L13: INVENTORY REPORT | N13: INVENTORY SUMMARY FROM DATE TO DATE

Sheet Products
A1: Barcode/Item Code | B1: Item Name | C1: Category | D1: Brand | E1: Size | F1: Color | G1: Cost | H1: Price | I1: Stock | J1: Low Alert
A2: 1001 | B2: NS-52 | C2: Fancy | D2: IG | E2: SML | F2: Black | G2: 2100 | H2: 1500 | I2: 40 | J2: 6
A3: 1002 | B3: R/S Crush | C3: Fancy | D3: SK | E3: SML | F3: Gray | G3: 2200 | H3: 2400 | I3: 20 | J3: 6
A4: 1003 | B4: PC 2PCS | C4: Casual | D4: CITI | E4: STD | F4: Pink | G4: 1100 | H4: 1500 | I4: 40 | J4: 24
A5: 1004 | B5: PC 3PCS | C5: Casual | D5: CITI | E5: STD | F5: Cheeko | G5: 1050 | H5: 1500 | I5: 45 | J5: 24
A6: 1005 | B6: PV 2PCS | C6: Casual | D6: DEBAJ | E6: STD | F6: Aqua | G6: 1100 | H6: 1500 | I6: 28 | J6: 24
A7: 1006 | B7: PV 3PCS | C7: Casual | D7: DEBAJ | E7: STD | F7: Mehroon | G7: 1150 | H7: 1500 | I7: 12 | J7: 24

Sheet Customers
A1: ID | B1: Name | C1: CONTACT | D1: WHATSAPP
A2: CUS-0001 | B2: WIC | C2: 333-0000001 | D2: 333-0000001
A3: CUS-0002 | B3: MAJID | C3: 333-0000001 | D3: 333-0000001
A4: CUS-0003 | B4: FASIH | C4: 333-0000001 | D4: 333-0000001
A5: CUS-0004 | B5: ARSHAD | C5: 333-0000001 | D5: 333-0000001

Sheet Suppliers
A1: SupplierID | B1: Supplier | C1: Phone | D1: Address
A2: VEND-0001 | B2: IG GARMENTS | C2: 333-0000001 | D2: KC
A3: VEND-0002 | B3: DEBAJ | C3: 333-0000001 | D3: KC
A4: VEND-0003 | B4: IB FASHION | C4: 333-0000001 | D4: KC

Sheet Sales
A1: Invoice | B1: Date | C1: Cashier | D1: Customer | E1: Barcode/Item Code | F1: Product | G1: Qty | H1: Price | I1: Discount | J1: Net | K1: Profit
A2: INV-000001 | B2: 46174 | C2: ISHAQ | D2: WIC | E2: 1002 | F2: =IFERROR(VLOOKUP(E2,Products!A:B,2,FALSE),"") -> R/S Crush | G2: 1 | H2: =IFERROR(VLOOKUP(E2,Products!A:H,8,FALSE),"") -> 2400 | I2: 100 | J2: =IFERROR((G2*H2-I2),"") -> 2300 | K2: =IFERROR((H2-VLOOKUP(E2,Products!A:G,7,FALSE))*G2,"") -> 200
A3: INV-000002 | B3: 46175 | C3: GUL | D3: FASIH | E3: 1003 | F3: =IFERROR(VLOOKUP(E3,Products!A:B,2,FALSE),"") -> PC 2PCS | G3: 1 | H3: =IFERROR(VLOOKUP(E3,Products!A:H,8,FALSE),"") -> 1500 | I3: 0 | J3: =IFERROR((G3*H3-I3),"") -> 1500 | K3: =IFERROR((H3-VLOOKUP(E3,Products!A:G,7,FALSE))*G3,"") -> 400
A4: INV-000003 | B4: 46176 | C4: ISHAQ | D4: ARSHAD | E4: 1004 | F4: =IFERROR(VLOOKUP(E4,Products!A:B,2,FALSE),"") -> PC 3PCS | G4: 1 | H4: =IFERROR(VLOOKUP(E4,Products!A:H,8,FALSE),"") -> 1500 | I4: 0 | J4: =IFERROR((G4*H4-I4),"") -> 1500 | K4: =IFERROR((H4-VLOOKUP(E4,Products!A:G,7,FALSE))*G4,"") -> 450
A5: INV-000004 | B5: 46177 | C5: ISHAQ | D5: WIC | E5: 1005 | F5: =IFERROR(VLOOKUP(E5,Products!A:B,2,FALSE),"") -> PV 2PCS | G5: 1 | H5: =IFERROR(VLOOKUP(E5,Products!A:H,8,FALSE),"") -> 1500 | I5: 0 | J5: =IFERROR((G5*H5-I5),"") -> 1500 | K5: =IFERROR((H5-VLOOKUP(E5,Products!A:G,7,FALSE))*G5,"") -> 400
A6: INV-000005 | B6: 46178 | C6: GUL | D6: WIC | E6: 1001 | F6: =IFERROR(VLOOKUP(E6,Products!A:B,2,FALSE),"") -> NS-52 | G6: 1 | H6: 3000 | I6: 200 | J6: =IFERROR((G6*H6-I6),"") -> 2800 | K6: =IFERROR((H6-VLOOKUP(E6,Products!A:G,7,FALSE))*G6,"") -> 900
F7: =IFERROR(VLOOKUP(E7,Products!A:B,2,FALSE),"") | H7: =IFERROR(VLOOKUP(E7,Products!A:H,8,FALSE),"") | J7: =IFERROR((G7*H7-I7),"") | K7: =IFERROR((H7-VLOOKUP(E7,Products!A:G,7,FALSE))*G7,"")
F8: =IFERROR(VLOOKUP(E8,Products!A:B,2,FALSE),"") | H8: =IFERROR(VLOOKUP(E8,Products!A:H,8,FALSE),"") | J8: =IFERROR((G8*H8-I8),"") | K8: =IFERROR((H8-VLOOKUP(E8,Products!A:G,7,FALSE))*G8,"")
F9: =IFERROR(VLOOKUP(E9,Products!A:B,2,FALSE),"") | H9: =IFERROR(VLOOKUP(E9,Products!A:H,8,FALSE),"") | J9: =IFERROR((G9*H9-I9),"") | K9: =IFERROR((H9-VLOOKUP(E9,Products!A:G,7,FALSE))*G9,"")
F10: =IFERROR(VLOOKUP(E10,Products!A:B,2,FALSE),"") | H10: =IFERROR(VLOOKUP(E10,Products!A:H,8,FALSE),"") | J10: =IFERROR((G10*H10-I10),"") | K10: =IFERROR((H10-VLOOKUP(E10,Products!A:G,7,FALSE))*G10,"")
F11: =IFERROR(VLOOKUP(E11,Products!A:B,2,FALSE),"") | H11: =IFERROR(VLOOKUP(E11,Products!A:H,8,FALSE),"") | J11: =IFERROR((G11*H11-I11),"") | K11: =IFERROR((H11-VLOOKUP(E11,Products!A:G,7,FALSE))*G11,"")
F12: =IFERROR(VLOOKUP(E12,Products!A:B,2,FALSE),"") | H12: =IFERROR(VLOOKUP(E12,Products!A:H,8,FALSE),"") | J12: =IFERROR((G12*H12-I12),"") | K12: =IFERROR((H12-VLOOKUP(E12,Products!A:G,7,FALSE))*G12,"")
F13: =IFERROR(VLOOKUP(E13,Products!A:B,2,FALSE),"") | H13: =IFERROR(VLOOKUP(E13,Products!A:H,8,FALSE),"") | J13: =IFERROR((G13*H13-I13),"") | K13: =IFERROR((H13-VLOOKUP(E13,Products!A:G,7,FALSE))*G13,"")
F14: =IFERROR(VLOOKUP(E14,Products!A:B,2,FALSE),"") | H14: =IFERROR(VLOOKUP(E14,Products!A:H,8,FALSE),"") | J14: =IFERROR((G14*H14-I14),"") | K14: =IFERROR((H14-VLOOKUP(E14,Products!A:G,7,FALSE))*G14,"")
F15: =IFERROR(VLOOKUP(E15,Products!A:B,2,FALSE),"") | H15: =IFERROR(VLOOKUP(E15,Products!A:H,8,FALSE),"") | J15: =IFERROR((G15*H15-I15),"") | K15: =IFERROR((H15-VLOOKUP(E15,Products!A:G,7,FALSE))*G15,"")
F16: =IFERROR(VLOOKUP(E16,Products!A:B,2,FALSE),"") | H16: =IFERROR(VLOOKUP(E16,Products!A:H,8,FALSE),"") | J16: =IFERROR((G16*H16-I16),"") | K16: =IFERROR((H16-VLOOKUP(E16,Products!A:G,7,FALSE))*G16,"")
F17: =IFERROR(VLOOKUP(E17,Products!A:B,2,FALSE),"") | H17: =IFERROR(VLOOKUP(E17,Products!A:H,8,FALSE),"") | J17: =IFERROR((G17*H17-I17),"") | K17: =IFERROR((H17-VLOOKUP(E17,Products!A:G,7,FALSE))*G17,"")
F18: =IFERROR(VLOOKUP(E18,Products!A:B,2,FALSE),"") | H18: =IFERROR(VLOOKUP(E18,Products!A:H,8,FALSE),"") | J18: =IFERROR((G18*H18-I18),"") | K18: =IFERROR((H18-VLOOKUP(E18,Products!A:G,7,FALSE))*G18,"")
... F500: =IFERROR(VLOOKUP(E500,Products!A:B,2,FALSE),"") | H500: =IFERROR(VLOOKUP(E500,Products!A:H,8,FALSE),"") | J500: =IFERROR((G500*H500-I500),"") | K500: =IFERROR((H500-VLOOKUP(E500,Products!A:G,7,FALSE))*G500,"")

Sheet Purchases
A1: PO ID | B1: PO Date | C1: VEND BILL | D1: BILL DATE | E1: VEND ID | F1: Supplier | G1: Barcode/Item Code | H1: Item Name | I1: Category | J1: Brand | K1: Size | L1: Color | M1: Qty | N1: Rate | O1: Amount
A2: PO-000001 | B2: 46174 | C2: 1 | D2: 46174 | E2: VEND-0001 | F2: =IFERROR(VLOOKUP(E2,Suppliers!A:D,2,FALSE),"") -> IG GARMENTS | G2: 1002 | H2: =IFERROR(VLOOKUP($G2,Products!$A:$J,2,FALSE),"") -> R/S Crush | I2: =IFERROR(VLOOKUP($G2,Products!$A:$J,3,FALSE),"") -> Fancy | J2: =IFERROR(VLOOKUP($G2,Products!$A:$J,4,FALSE),"") -> SK | K2: =IFERROR(VLOOKUP($G2,Products!$A:$J,5,FALSE),"") -> SML | L2: =IFERROR(VLOOKUP($G2,Products!$A:$J,6,FALSE),"") -> Gray | M2: 3 | N2: =IFERROR(VLOOKUP($G2,Products!$A:$J,7,FALSE),"") -> 2200 | O2: =M2*N2 -> 6600
A3: PO-000002 | B3: 46174 | C3: 2 | D3: 46174 | E3: VEND-0001 | F3: =IFERROR(VLOOKUP(E3,Suppliers!A:D,2,FALSE),"") -> IG GARMENTS | G3: 1004 | H3: =IFERROR(VLOOKUP(G3,Products!A:J,2,FALSE),"") -> PC 3PCS | I3: =IFERROR(VLOOKUP(H3,Products!B:K,2,FALSE),"") -> Casual | J3: =IFERROR(VLOOKUP(I3,Products!C:L,2,FALSE),"") -> CITI | K3: =IFERROR(VLOOKUP(J3,Products!D:M,2,FALSE),"") -> STD | L3: =IFERROR(VLOOKUP(K3,Products!E:N,2,FALSE),"") -> Pink | M3: 6 | N3: =IFERROR(VLOOKUP($G3,Products!$A:$J,7,FALSE),"") -> 1050 | O3: =M3*N3 -> 6300
A4: PO-000003 | B4: 46174 | C4: 3 | D4: 46174 | E4: VEND-0003 | F4: =IFERROR(VLOOKUP(E4,Suppliers!A:D,2,FALSE),"") -> IB FASHION | G4: 1005 | H4: =IFERROR(VLOOKUP(G4,Products!A:J,2,FALSE),"") -> PV 2PCS | I4: =IFERROR(VLOOKUP(H4,Products!B:K,2,FALSE),"") -> Casual | J4: =IFERROR(VLOOKUP(I4,Products!C:L,2,FALSE),"") -> CITI | K4: =IFERROR(VLOOKUP(J4,Products!D:M,2,FALSE),"") -> STD | L4: =IFERROR(VLOOKUP(K4,Products!E:N,2,FALSE),"") -> Pink | M4: 6 | N4: =IFERROR(VLOOKUP($G4,Products!$A:$J,7,FALSE),"") -> 1100 | O4: =M4*N4 -> 6600
A5: PO-000004 | B5: 46174 | C5: 4 | D5: 46174 | E5: VEND-0002 | F5: =IFERROR(VLOOKUP(E5,Suppliers!A:D,2,FALSE),"") -> DEBAJ | G5: 1002 | H5: =IFERROR(VLOOKUP(G5,Products!A:J,2,FALSE),"") -> R/S Crush | I5: =IFERROR(VLOOKUP(H5,Products!B:K,2,FALSE),"") -> Fancy | J5: =IFERROR(VLOOKUP(I5,Products!C:L,2,FALSE),"") -> IG | K5: =IFERROR(VLOOKUP(J5,Products!D:M,2,FALSE),"") -> SML | L5: =IFERROR(VLOOKUP(K5,Products!E:N,2,FALSE),"") -> Black | M5: 2 | N5: =IFERROR(VLOOKUP($G5,Products!$A:$J,7,FALSE),"") -> 2200 | O5: =M5*N5 -> 4400

Sheet Inventory
A1: SKU | B1: Product | C1: Category | D1: Brand | E1: Size | F1: Color | G1: Opening | H1: Purchased | I1: Sold | J1: Closing | K1: Status
A2: =Products!A2 -> 1001 | B2: =IFERROR(VLOOKUP($A2,Products!$A:$G,2,FALSE),"") -> NS-52 | C2: =IFERROR(VLOOKUP($A2,Products!$A:$G,3,FALSE),"") -> Fancy | D2: =IFERROR(VLOOKUP($A2,Products!$A:$G,4,FALSE),"") -> IG | E2: =IFERROR(VLOOKUP($A2,Products!$A:$G,5,FALSE),"") -> SML | F2: =IFERROR(VLOOKUP($A2,Products!$A:$G,6,FALSE),"") -> Black | G2: =Products!I2 -> 40 | H2: =SUMIF(Purchases!H:H,A2,Purchases!M:M) -> 0 | I2: =SUMIF(Sales!E:E,A2,Sales!G:G) -> 1 | J2: =G2+H2-I2 -> 39 | K2: =IF(J2<=Products!J2,"LOW STOCK","OK") -> OK
A3: =Products!A3 -> 1002 | B3: =IFERROR(VLOOKUP($A3,Products!$A:$G,2,FALSE),"") -> R/S Crush | C3: =IFERROR(VLOOKUP($A3,Products!$A:$G,3,FALSE),"") -> Fancy | D3: =IFERROR(VLOOKUP($A3,Products!$A:$G,4,FALSE),"") -> SK | E3: =IFERROR(VLOOKUP($A3,Products!$A:$G,5,FALSE),"") -> SML | F3: =IFERROR(VLOOKUP($A3,Products!$A:$G,6,FALSE),"") -> Gray | G3: =Products!I3 -> 20 | H3: =SUMIF(Purchases!H:H,A3,Purchases!M:M) -> 0 | I3: =SUMIF(Sales!E:E,A3,Sales!G:G) -> 1 | J3: =G3+H3-I3 -> 19 | K3: =IF(J3<=Products!J3,"LOW STOCK","OK") -> OK
A4: =Products!A4 -> 1003 | B4: =IFERROR(VLOOKUP($A4,Products!$A:$G,2,FALSE),"") -> PC 2PCS | C4: =IFERROR(VLOOKUP($A4,Products!$A:$G,3,FALSE),"") -> Casual | D4: =IFERROR(VLOOKUP($A4,Products!$A:$G,4,FALSE),"") -> CITI | E4: =IFERROR(VLOOKUP($A4,Products!$A:$G,5,FALSE),"") -> STD | F4: =IFERROR(VLOOKUP($A4,Products!$A:$G,6,FALSE),"") -> Pink | G4: =Products!I4 -> 40 | H4: =SUMIF(Purchases!H:H,A4,Purchases!M:M) -> 0 | I4: =SUMIF(Sales!E:E,A4,Sales!G:G) -> 1 | J4: =G4+H4-I4 -> 39 | K4: =IF(J4<=Products!J4,"LOW STOCK","OK") -> OK
A5: =Products!A5 -> 1004 | B5: =IFERROR(VLOOKUP($A5,Products!$A:$G,2,FALSE),"") -> PC 3PCS | C5: =IFERROR(VLOOKUP($A5,Products!$A:$G,3,FALSE),"") -> Casual | D5: =IFERROR(VLOOKUP($A5,Products!$A:$G,4,FALSE),"") -> CITI | E5: =IFERROR(VLOOKUP($A5,Products!$A:$G,5,FALSE),"") -> STD | F5: =IFERROR(VLOOKUP($A5,Products!$A:$G,6,FALSE),"") -> Cheeko | G5: =Products!I5 -> 45 | H5: =SUMIF(Purchases!H:H,A5,Purchases!M:M) -> 0 | I5: =SUMIF(Sales!E:E,A5,Sales!G:G) -> 1 | J5: =G5+H5-I5 -> 44 | K5: =IF(J5<=Products!J5,"LOW STOCK","OK") -> OK
A6: =Products!A6 -> 1005 | B6: =IFERROR(VLOOKUP($A6,Products!$A:$G,2,FALSE),"") -> PV 2PCS | C6: =IFERROR(VLOOKUP($A6,Products!$A:$G,3,FALSE),"") -> Casual | D6: =IFERROR(VLOOKUP($A6,Products!$A:$G,4,FALSE),"") -> DEBAJ | E6: =IFERROR(VLOOKUP($A6,Products!$A:$G,5,FALSE),"") -> STD | F6: =IFERROR(VLOOKUP($A6,Products!$A:$G,6,FALSE),"") -> Aqua | G6: =Products!I6 -> 28 | H6: =SUMIF(Purchases!H:H,A6,Purchases!M:M) -> 0 | I6: =SUMIF(Sales!E:E,A6,Sales!G:G) -> 1 | J6: =G6+H6-I6 -> 27 | K6: =IF(J6<=Products!J6,"LOW STOCK","OK") -> OK
A7: =Products!A7 -> 1006 | B7: =IFERROR(VLOOKUP($A7,Products!$A:$G,2,FALSE),"") -> PV 3PCS | C7: =IFERROR(VLOOKUP($A7,Products!$A:$G,3,FALSE),"") -> Casual | D7: =IFERROR(VLOOKUP($A7,Products!$A:$G,4,FALSE),"") -> DEBAJ | E7: =IFERROR(VLOOKUP($A7,Products!$A:$G,5,FALSE),"") -> STD | F7: =IFERROR(VLOOKUP($A7,Products!$A:$G,6,FALSE),"") -> Mehroon | G7: =Products!I7 -> 12 | H7: =SUMIF(Purchases!H:H,A7,Purchases!M:M) -> 0 | I7: =SUMIF(Sales!E:E,A7,Sales!G:G) -> 0 | J7: =G7+H7-I7 -> 12 | K7: =IF(J7<=Products!J7,"LOW STOCK","OK") -> LOW STOCK
A8: =Products!A8 -> 0 | B8: =IFERROR(VLOOKUP($A8,Products!$A:$G,2,FALSE),"") | G8: =Products!I8 -> 0 | H8: =SUMIF(Purchases!H:H,A8,Purchases!M:M) -> 0 | I8: =SUMIF(Sales!E:E,A8,Sales!G:G) -> 0 | J8: =G8+H8-I8 -> 0 | K8: =IF(J8<=Products!J8,"LOW STOCK","OK") -> LOW STOCK
A9: =Products!A9 -> 0 | B9: =IFERROR(VLOOKUP($A9,Products!$A:$G,2,FALSE),"") | G9: =Products!I9 -> 0 | H9: =SUMIF(Purchases!H:H,A9,Purchases!M:M) -> 0 | I9: =SUMIF(Sales!E:E,A9,Sales!G:G) -> 0 | J9: =G9+H9-I9 -> 0 | K9: =IF(J9<=Products!J9,"LOW STOCK","OK") -> LOW STOCK
A10: =Products!A10 -> 0 | B10: =IFERROR(VLOOKUP($A10,Products!$A:$G,2,FALSE),"") | G10: =Products!I10 -> 0 | H10: =SUMIF(Purchases!H:H,A10,Purchases!M:M) -> 0 | I10: =SUMIF(Sales!E:E,A10,Sales!G:G) -> 0 | J10: =G10+H10-I10 -> 0 | K10: =IF(J10<=Products!J10,"LOW STOCK","OK") -> LOW STOCK
A11: =Products!A11 -> 0 | B11: =IFERROR(VLOOKUP($A11,Products!$A:$G,2,FALSE),"") | G11: =Products!I11 -> 0 | H11: =SUMIF(Purchases!H:H,A11,Purchases!M:M) -> 0 | I11: =SUMIF(Sales!E:E,A11,Sales!G:G) -> 0 | J11: =G11+H11-I11 -> 0 | K11: =IF(J11<=Products!J11,"LOW STOCK","OK") -> LOW STOCK
A12: =Products!A12 -> 0 | B12: =IFERROR(VLOOKUP($A12,Products!$A:$G,2,FALSE),"") | G12: =Products!I12 -> 0 | H12: =SUMIF(Purchases!H:H,A12,Purchases!M:M) -> 0 | I12: =SUMIF(Sales!E:E,A12,Sales!G:G) -> 0 | J12: =G12+H12-I12 -> 0 | K12: =IF(J12<=Products!J12,"LOW STOCK","OK") -> LOW STOCK
A13: =Products!A13 -> 0 | B13: =IFERROR(VLOOKUP($A13,Products!$A:$G,2,FALSE),"") | G13: =Products!I13 -> 0 | H13: =SUMIF(Purchases!H:H,A13,Purchases!M:M) -> 0 | I13: =SUMIF(Sales!E:E,A13,Sales!G:G) -> 0 | J13: =G13+H13-I13 -> 0 | K13: =IF(J13<=Products!J13,"LOW STOCK","OK") -> LOW STOCK
A14: =Products!A14 -> 0 | B14: =IFERROR(VLOOKUP($A14,Products!$A:$G,2,FALSE),"") | G14: =Products!I14 -> 0 | H14: =SUMIF(Purchases!H:H,A14,Purchases!M:M) -> 0 | I14: =SUMIF(Sales!E:E,A14,Sales!G:G) -> 0 | J14: =G14+H14-I14 -> 0 | K14: =IF(J14<=Products!J14,"LOW STOCK","OK") -> LOW STOCK
A15: =Products!A15 -> 0 | B15: =IFERROR(VLOOKUP($A15,Products!$A:$G,2,FALSE),"") | G15: =Products!I15 -> 0 | H15: =SUMIF(Purchases!H:H,A15,Purchases!M:M) -> 0 | I15: =SUMIF(Sales!E:E,A15,Sales!G:G) -> 0 | J15: =G15+H15-I15 -> 0 | K15: =IF(J15<=Products!J15,"LOW STOCK","OK") -> LOW STOCK
A16: =Products!A16 -> 0 | B16: =IFERROR(VLOOKUP($A16,Products!$A:$G,2,FALSE),"") | G16: =Products!I16 -> 0 | H16: =SUMIF(Purchases!H:H,A16,Purchases!M:M) -> 0 | I16: =SUMIF(Sales!E:E,A16,Sales!G:G) -> 0 | J16: =G16+H16-I16 -> 0 | K16: =IF(J16<=Products!J16,"LOW STOCK","OK") -> LOW STOCK
A17: =Products!A17 -> 0 | B17: =IFERROR(VLOOKUP($A17,Products!$A:$G,2,FALSE),"") | G17: =Products!I17 -> 0 | H17: =SUMIF(Purchases!H:H,A17,Purchases!M:M) -> 0 | I17: =SUMIF(Sales!E:E,A17,Sales!G:G) -> 0 | J17: =G17+H17-I17 -> 0 | K17: =IF(J17<=Products!J17,"LOW STOCK","OK") -> LOW STOCK
A18: =Products!A18 -> 0 | B18: =IFERROR(VLOOKUP($A18,Products!$A:$G,2,FALSE),"") | G18: =Products!I18 -> 0 | H18: =SUMIF(Purchases!H:H,A18,Purchases!M:M) -> 0 | I18: =SUMIF(Sales!E:E,A18,Sales!G:G) -> 0 | J18: =G18+H18-I18 -> 0 | K18: =IF(J18<=Products!J18,"LOW STOCK","OK") -> LOW STOCK
A19: =Products!A19 -> 0 | B19: =IFERROR(VLOOKUP($A19,Products!$A:$G,2,FALSE),"") | G19: =Products!I19 -> 0 | H19: =SUMIF(Purchases!H:H,A19,Purchases!M:M) -> 0 | I19: =SUMIF(Sales!E:E,A19,Sales!G:G) -> 0 | J19: =G19+H19-I19 -> 0 | K19: =IF(J19<=Products!J19,"LOW STOCK","OK") -> LOW STOCK
... A300: =Products!A300 -> 0 | B300: =IFERROR(VLOOKUP($A300,Products!$A:$G,2,FALSE),"") | G300: =Products!I300 -> 0 | H300: =SUMIF(Purchases!H:H,A300,Purchases!M:M) -> 0 | I300: =SUMIF(Sales!E:E,A300,Sales!G:G) -> 0 | J300: =G300+H300-I300 -> 0 | K300: =IF(J300<=Products!J300,"LOW STOCK","OK") -> LOW STOCK

Sheet Thermal_Receipt
A1: *** SHOP NAME ***
A3: Invoice:
A5: Item Qty Price
A15: Thank You!
